pydoc_markdown_havsalt/__init__.py
pydoc_markdown_havsalt/processors.py
pydoc_markdown_havsalt/py.typed
pydoc_markdown_havsalt/renderers.py
pydoc_markdown_havsalt-0.1.3.dist-info/METADATA
pydoc_markdown_havsalt-0.1.3.dist-info/WHEEL
pydoc_markdown_havsalt-0.1.3.dist-info/licenses/LICENSE
pydoc_markdown_havsalt-0.1.3.dist-info/RECORD
