Metadata-Version: 2.4
Name: pydoc-markdown-havsalt
Version: 0.1.3
Summary: Plugin for pydoc-markdown
Author-email: Havsalt <77575424+Havsalt@users.noreply.github.com>
License: MIT License
License-File: LICENSE
Keywords: documentation,plugin
Requires-Python: >=3.10
Requires-Dist: pydoc-markdown>=4.0.0
